Workbook

Sheet Income statement
A1: NORTHROP GRUMMAN CORPORATION
A2: CONSOLIDATED STATEMENTS OF EARNINGS AND COMPREHENSIVE INCOME
A3: $ in millions, except per share amounts
B4: 2023 | C4: 2024 | D4: 2025 | E4: =D4+1 -> 2026 | F4: =E4+1 -> 2027 | G4: =F4+1 -> 2028 | H4: =G4+1 -> 2029 | I4: =H4+1 -> 2030
A6: Sales
A7: Net sales | B7: 39290 | C7: 41033 | D7: 41954 | E7: 44000 | F7: =E7*(1+F8) -> 45980 | G7: =F7*(1+G8) -> 48049.1 | H7: =G7*(1+H8) -> 50211.309 | I7: =H7*(1+I8) -> 52470.818
A8: Y/Y Net sales growth rate | C8: =C7/B7-1 -> 0.044362433 | D8: =D7/C7-1 -> 0.022445349 | E8: =E7/D7-1 -> 0.048767698 | F8: 0.045 | G8: 0.045 | H8: 0.045 | I8: 0.045
A10: Operating expenses
A11: Cost of sales | B11: 31555 | C11: 31494 | D11: 32437 | E11: =E7*E12 -> 34375.96 | F11: =F7*F12 -> 35922.878 | G11: =G7*G12 -> 37539.408 | H11: =H7*H12 -> 39228.681 | I11: =I7*I12 -> 40993.972
A12: COS as a % of net sales | B12: =B11/B7 -> 0.80313057 | C12: =C11/C7 -> 0.76752857 | D12: =D11/D7 -> 0.77315631 | E12: =AVERAGE($B$12:$D$12) -> 0.78127182 | F12: =AVERAGE($B$12:$D$12) -> 0.78127182 | G12: =AVERAGE($B$12:$D$12) -> 0.78127182 | H12: =AVERAGE($B$12:$D$12) -> 0.78127182 | I12: =AVERAGE($B$12:$D$12) -> 0.78127182
A13: Gross profit | B13: =B7-B11 -> 7735 | C13: =C7-C11 -> 9539 | D13: =D7-D11 -> 9517 | E13: =E7-E11 -> 9624.04 | F13: =F7-F11 -> 10057.122 | G13: =G7-G11 -> 10509.692 | H13: =H7-H11 -> 10982.628 | I13: =I7-I11 -> 11476.847
A14: Gross margin | B14: =B13/B7 -> 0.19686943 | C14: =C13/C7 -> 0.23247143 | D14: =D13/D7 -> 0.22684369 | E14: =E13/E7 -> 0.21872818 | F14: =F13/F7 -> 0.21872818 | G14: =G13/G7 -> 0.21872818 | H14: =H13/H7 -> 0.21872818 | I14: =I13/I7 -> 0.21872818
A16: General and administrative costs | B16: 3860 | C16: 3799 | D16: 3765 | E16: =E7*E17 -> 4115.0119 | F16: =F7*F17 -> 4300.1874 | G16: =G7*G17 -> 4493.6958 | H16: =H7*H17 -> 4695.9121 | I16: =I7*I17 -> 4907.2282
A17: General & admin. as % of net sales | B17: =B16/B7 -> 0.098243828 | C17: =C16/C7 -> 0.092584018 | D17: =D16/D7 -> 0.089741145 | E17: =AVERAGE($B$17:$D$17) -> 0.093522997 | F17: =AVERAGE($B$17:$D$17) -> 0.093522997 | G17: =AVERAGE($B$17:$D$17) -> 0.093522997 | H17: =AVERAGE($B$17:$D$17) -> 0.093522997 | I17: =AVERAGE($B$17:$D$17) -> 0.093522997
A18: Total operating expenses | B18: =B16 -> 3860 | C18: =C16 -> 3799 | D18: =D16 -> 3765 | E18: =E16 -> 4115.0119 | F18: =F16 -> 4300.1874 | G18: =G16 -> 4493.6958 | H18: =H16 -> 4695.9121 | I18: =I16 -> 4907.2282
A20: EBITDA | B20: =B13-B16 -> 3875 | C20: =C13-C16 -> 5740 | D20: =D13-D16 -> 5752 | E20: =E13-E16 -> 5509.0281 | F20: =F13-F16 -> 5756.9344 | G20: =G13-G16 -> 6015.9964 | H20: =H13-H16 -> 6286.7163 | I20: =I13-I16 -> 6569.6185
A21: EBITDA margin | B21: =B20/B7 -> 0.098625604 | C21: =C20/C7 -> 0.13988741 | D21: =D20/D7 -> 0.13710254
A22: Depreciation and amortization | B22: 1338 | C22: 1370 | D22: 1472 | E22: ='PPE schedule'!E11 -> 1572.3292 | F22: ='PPE schedule'!F11 -> 1680.7893 | G22: ='PPE schedule'!G11 -> 1794.1301 | H22: ='PPE schedule'!H11 -> 1912.5712 | I22: ='PPE schedule'!I11 -> 2036.3422
A24: Operating income (EBIT) | B24: =B20-B22 -> 2537 | C24: =C20-C22 -> 4370 | D24: =D20-D22 -> 4280 | E24: =E20-E22 -> 3936.6989 | F24: =F20-F22 -> 4076.145 | G24: =G20-G22 -> 4221.8663 | H24: =H20-H22 -> 4374.145 | I24: =I20-I22 -> 4533.2763
A25: EBIT margin | B25: =B24/B7 -> 0.064571138 | C25: =C24/C7 -> 0.10649965 | D25: =D24/D7 -> 0.10201649 | E25: =E24/E7 -> 0.089470429 | F25: =F24/F7 -> 0.088650393 | G25: =G24/G7 -> 0.087865669 | H25: =H24/H7 -> 0.087114737 | I25: =I24/I7 -> 0.086396142
A27: Gain on sale of business | D27: 231
A29: Operation income
A30: Interest expense | B30: -545 | C30: -621 | D30: -665 | E30: =-1*'Debt schedule'!E11 -> -642.98246 | F30: =-1*'Debt schedule'!F11 -> -642.98246 | G30: =-1*'Debt schedule'!G11 -> -642.98246 | H30: =-1*'Debt schedule'!H11 -> -642.98246 | I30: =-1*'Debt schedule'!I11 -> -642.98246
A32: Non-operating FAS pension benefit | B32: 530 | C32: 656 | D32: 541 | E32: 665 | F32: 665 | G32: 665 | H32: 665 | I32: 665
A34: Mark-to-market pension & OPB benefit | B34: -422 | C34: 443 | D34: 527 | E34: 0 | F34: 0 | G34: 0 | H34: 0 | I34: 0
A36: other income/expense | B36: 246 | C36: 168 | D36: 154 | E36: =AVERAGE($B$36:$D$36) -> 189.33333 | F36: =AVERAGE($B$36:$D$36) -> 189.33333 | G36: =AVERAGE($B$36:$D$36) -> 189.33333 | H36: =AVERAGE($B$36:$D$36) -> 189.33333 | I36: =AVERAGE($B$36:$D$36) -> 189.33333
A38: Pre-tax income | B38: =B24+B27+B30+B32+B34+B36 -> 2346 | C38: =C24+C27+C30+C32+C34+C36 -> 5016 | D38: =D24+D27+D30+D32+D34+D36 -> 5068 | E38: =E24+E27+E30+E32+E34+E36 -> 4148.0497 | F38: =F24+F27+F30+F32+F34+F36 -> 4287.4959 | G38: =G24+G27+G30+G32+G34+G36 -> 4433.2172 | H38: =H24+H27+H30+H32+H34+H36 -> 4585.4959 | I38: =I24+I27+I30+I32+I34+I36 -> 4744.6272
A39: EBT margin | B39: =B38/B7 -> 0.05970985 | C39: =C38/C7 -> 0.12224307 | D39: =D38/D7 -> 0.12079897 | E39: =E38/E7 -> 0.094273858 | F39: =F38/F7 -> 0.093246975 | G39: =G38/G7 -> 0.092264313 | H39: =H38/H7 -> 0.091323966 | I39: =I38/I7 -> 0.090424112
A41: income tax expense (Federal and Foreign) | B41: 290 | C41: 842 | D41: 886 | E41: =E38*E42 -> 705.16846 | F41: =F38*F42 -> 728.87431 | G41: =G38*G42 -> 753.64692 | H41: =H38*H42 -> 779.5343 | I41: =I38*I42 -> 806.58662
A42: Effective tax rate | B42: =B41/B38 -> 0.12361466 | C42: =C41/C38 -> 0.16786284 | D42: =D41/D38 -> 0.17482242 | E42: 0.17 | F42: 0.17 | G42: 0.17 | H42: 0.17 | I42: 0.17
A44: Net income | B44: =B38-B41 -> 2056 | C44: =C38-C41 -> 4174 | D44: =D38-D41 -> 4182 | E44: =E38-E41 -> 3442.8813 | F44: =F38-F41 -> 3558.6216 | G44: =G38-G41 -> 3679.5703 | H44: =H38-H41 -> 3805.9616 | I44: =I38-I41 -> 3938.0405
A46: Other comprehensive income (loss), net of tax | B46: 25 | C46: -24 | D46: 26 | E46: 0 | F46: 0 | G46: 0 | H46: 0 | I46: 0
A48: Comprehensive income | B48: =B44+B46 -> 2081 | C48: =C44+C46 -> 4150 | D48: =D44+D46 -> 4208 | E48: =E44+E46 -> 3442.8813 | F48: =F44+F46 -> 3558.6216 | G48: =G44+G46 -> 3679.5703 | H48: =H44+H46 -> 3805.9616 | I48: =I44+I46 -> 3938.0405
A50: Basic earnings per share | B50: =B44/B52 -> 13.570957 | C50: =C44/C52 -> 28.394558 | D50: =D44/D52 -> 29.142857 | E50: =E44/E52 -> 24.357568 | F50: =F44/F52 -> 25.179075 | G50: =G44/G52 -> 26.037612 | H50: =H44/H52 -> 26.93485 | I50: =I44/I52 -> 27.872533
A51: Diluted earnings per share | B51: =B44/B53 -> 13.526316 | C51: =C44/C53 -> 28.336728 | D51: =D44/D53 -> 29.082058 | E51: =E44/E53 -> 24.306752 | F51: =F44/F53 -> 25.12654 | G51: =G44/G53 -> 25.98328 | H51: =H44/H53 -> 26.87864 | I51: =I44/I53 -> 27.81436
A52: Basic | B52: 151.5 | C52: 147 | D52: 143.5 | E52: =D52*(1-1.5%) -> 141.3475 | F52: =E52-1.5% -> 141.3325 | G52: =F52-1.5% -> 141.3175 | H52: =G52-1.5% -> 141.3025 | I52: =H52-1.5% -> 141.2875
A53: Diluted | B53: 152 | C53: 147.3 | D53: 143.8 | E53: =D53*(1-1.5%) -> 141.643 | F53: =E53-1.5% -> 141.628 | G53: =F53-1.5% -> 141.613 | H53: =G53-1.5% -> 141.598 | I53: =H53-1.5% -> 141.583

Sheet Cash Flow statement
A1: NORTHROP GRUMMAN CORPORATION
A2: CONSOLIDATED STATEMENTS OF CASH FLOWS
A3: $ in millions
B4: 2023 | C4: 2024 | D4: 2025 | E4: =D4+1 -> 2026 | F4: =E4+1 -> 2027 | G4: =F4+1 -> 2028 | H4: =G4+1 -> 2029 | I4: =H4+1 -> 2030
A6: Operating activities:
A7: Net income | B7: ='Income statement'!B44 -> 2056 | C7: ='Income statement'!C44 -> 4174 | D7: ='Income statement'!D44 -> 4182 | E7: ='Income statement'!E44 -> 3442.8813 | F7: ='Income statement'!F44 -> 3558.6216 | G7: ='Income statement'!G44 -> 3679.5703 | H7: ='Income statement'!H44 -> 3805.9616 | I7: ='Income statement'!I44 -> 3938.0405
A8: Adjustments to reconcile net income to net cash from operating actviites:
A10: Depreciation and amortization | B10: 1338 | C10: 1370 | D10: 1472 | E10: ='PPE schedule'!E11 -> 1572.3292 | F10: ='PPE schedule'!F11 -> 1680.7893 | G10: ='PPE schedule'!G11 -> 1794.1301 | H10: ='PPE schedule'!H11 -> 1912.5712 | I10: ='PPE schedule'!I11 -> 2036.3422
A11: Stock-based compensation | B11: 87 | C11: 101 | D11: 119 | E11: ='Income statement'!E7*'Cash Flow statement'!E12 -> 110.1786 | F11: ='Income statement'!F7*'Cash Flow statement'!F12 -> 115.13664 | G11: ='Income statement'!G7*'Cash Flow statement'!G12 -> 120.31779 | H11: ='Income statement'!H7*'Cash Flow statement'!H12 -> 125.73209 | I11: ='Income statement'!I7*'Cash Flow statement'!I12 -> 131.39003
A12: SBC as a % of sales | B12: =B11/'Income statement'!B7 -> 0.0022143039 | C12: =C11/'Income statement'!C7 -> 0.0024614335 | D12: =D11/'Income statement'!D7 -> 0.0028364399 | E12: =AVERAGE($B$12:$D$12) -> 0.0025040591 | F12: =AVERAGE($B$12:$D$12) -> 0.0025040591 | G12: =AVERAGE($B$12:$D$12) -> 0.0025040591 | H12: =AVERAGE($B$12:$D$12) -> 0.0025040591 | I12: =AVERAGE($B$12:$D$12) -> 0.0025040591
A13: Deferred income taxes | B13: -988 | C13: -582 | D13: 548
A14: B-21 loss provisions | B14: 1559 | D14: 477 | E14: 0 | F14: 0 | G14: 0 | H14: 0 | I14: 0
A15: Gain on sale of business | D15: -231
A16: Mark-to-market pension and OPB (benefit) expense | B16: 422 | C16: -443 | D16: -527 | E16: 0 | F16: 0 | G16: 0 | H16: 0 | I16: 0
A17: Net periodic pension and OPB income | B17: -308 | C17: -438 | D17: -346 | E17: =AVERAGE($B$17:$D$17) -> -364 | F17: =AVERAGE($B$17:$D$17) -> -364 | G17: =AVERAGE($B$17:$D$17) -> -364 | H17: =AVERAGE($B$17:$D$17) -> -364 | I17: =AVERAGE($B$17:$D$17) -> -364
A18: Pension and OPB contribtions | B18: -139 | C18: -129 | D18: -130 | E18: -131 | F18: -131 | G18: -131 | H18: -131 | I18: -131
A19: Changes in assets and liabilities:
A20: Accounts receivable, net | B20: 54 | C20: 182 | D20: -108 | E20: =-('Working capital schedule'!E7-'Working capital schedule'!D7) -> -140.47907 | F20: =-('Working capital schedule'!F7-'Working capital schedule'!E7) -> -68.196558 | G20: =-('Working capital schedule'!G7-'Working capital schedule'!F7) -> -71.265403 | H20: =-('Working capital schedule'!H7-'Working capital schedule'!G7) -> -74.472347 | I20: =-('Working capital schedule'!I7-'Working capital schedule'!H7) -> -77.823602
A21: Unbilled recievables, net | B21: 247 | C21: -215 | D21: -754 | E21: ='Working capital schedule'!D9-'Working capital schedule'!E9 -> 19.402022 | F21: ='Working capital schedule'!E9-'Working capital schedule'!F9 -> -293.60691 | G21: ='Working capital schedule'!F9-'Working capital schedule'!G9 -> -306.81922 | H21: ='Working capital schedule'!G9-'Working capital schedule'!H9 -> -320.62608 | I21: ='Working capital schedule'!H9-'Working capital schedule'!I9 -> -335.05426
A22: Inventoried costs, net | B22: -220 | C22: -358 | D22: 97 | E22: ='Working capital schedule'!D5-'Working capital schedule'!E5 -> -82.663023 | F22: ='Working capital schedule'!E5-'Working capital schedule'!F5 -> -62.624836 | G22: ='Working capital schedule'!F5-'Working capital schedule'!G5 -> -65.442954 | H22: ='Working capital schedule'!G5-'Working capital schedule'!H5 -> -68.387887 | I22: ='Working capital schedule'!H5-'Working capital schedule'!I5 -> -71.465341
A23: Prepaid expenses and other assets | B23: -86 | C23: 35 | D23: 8 | E23: ='Working capital schedule'!D11-'Working capital schedule'!E11 -> -256.46032 | F23: ='Working capital schedule'!E11-'Working capital schedule'!F11 -> -86.060714 | G23: ='Working capital schedule'!F11-'Working capital schedule'!G11 -> -89.933446 | H23: ='Working capital schedule'!G11-'Working capital schedule'!H11 -> -93.980452 | I23: ='Working capital schedule'!H11-'Working capital schedule'!I11 -> -98.209572
A24: Trade accounts payable | B24: -469 | C24: 485 | D24: 646 | E24: ='Working capital schedule'!E16-'Working capital schedule'!D16 -> -383.6217 | F24: ='Working capital schedule'!F16-'Working capital schedule'!E16 -> 128.53702 | G24: ='Working capital schedule'!G16-'Working capital schedule'!F16 -> 134.32119 | H24: ='Working capital schedule'!H16-'Working capital schedule'!G16 -> 140.36564 | I24: ='Working capital schedule'!I16-'Working capital schedule'!H16 -> 146.6821
A25: Advance payments & billings in excess of costs incurred (unearned revenue) | B25: 587 | C25: -123 | D25: 19 | E25: ='Working capital schedule'!E20-'Working capital schedule'!D20 -> 362.40157 | F25: ='Working capital schedule'!F20-'Working capital schedule'!E20 -> 200.17807 | G25: ='Working capital schedule'!G20-'Working capital schedule'!F20 -> 209.18608 | H25: ='Working capital schedule'!H20-'Working capital schedule'!G20 -> 218.59946 | I25: ='Working capital schedule'!I20-'Working capital schedule'!H20 -> 228.43643
A26: Other liabilities | B26: 401 | C26: -875 | D26: -212 | E26: ='Working capital schedule'!E24-'Working capital schedule'!D24 -> 87 | F26: ='Working capital schedule'!F24-'Working capital schedule'!E24 -> 0 | G26: ='Working capital schedule'!G24-'Working capital schedule'!F24 -> 0 | H26: ='Working capital schedule'!H24-'Working capital schedule'!G24 -> 0 | I26: ='Working capital schedule'!I24-'Working capital schedule'!H24 -> 0
A27: Income taxes payable, net | B27: -658 | C27: 1143 | D27: -559 | E27: ='Working capital schedule'!E22-'Working capital schedule'!D22 -> 534.33333 | F27: ='Working capital schedule'!F22-'Working capital schedule'!E22 -> 0 | G27: ='Working capital schedule'!G22-'Working capital schedule'!F22 -> 0 | H27: ='Working capital schedule'!H22-'Working capital schedule'!G22 -> 0 | I27: ='Working capital schedule'!I22-'Working capital schedule'!H22 -> 0
A28: Other operating activities | B28: -8 | C28: 61 | D28: 56 | E28: 0 | F28: 0 | G28: 0 | H28: 0 | I28: 0
A29: Net cash provided by operating ativities | B29: =B7+B10+B11+B13+B14+B15+B16+B17+B18+B20+B21+B22+B23+B24+B25+B26+B27+B28 -> 3875 | C29: =C7+C10+C11+C13+C14+C15+C16+C17+C18+C20+C21+C22+C23+C24+C25+C26+C27+C28 -> 4388 | D29: =D7+D10+D11+D13+D14+D15+D16+D17+D18+D20+D21+D22+D23+D24+D25+D26+D27+D28 -> 4757 | E29: =E7+E10+E11+E13+E14+E15+E16+E17+E18+E20+E21+E22+E23+E24+E25+E26+E27+E28 -> 4770.3019 | F29: =F7+F10+F11+F13+F14+F15+F16+F17+F18+F20+F21+F22+F23+F24+F25+F26+F27+F28 -> 4677.7737 | G29: =G7+G10+G11+G13+G14+G15+G16+G17+G18+G20+G21+G22+G23+G24+G25+G26+G27+G28 -> 4909.0644 | H29: =H7+H10+H11+H13+H14+H15+H16+H17+H18+H20+H21+H22+H23+H24+H25+H26+H27+H28 -> 5150.7633 | I29: =I7+I10+I11+I13+I14+I15+I16+I17+I18+I20+I21+I22+I23+I24+I25+I26+I27+I28 -> 5403.3385
A31: Investing activities:
A32: Capital expenditures | B32: -1775 | C32: -1767 | D32: -1450 | E32: =-'Income statement'!E7*'Cash Flow statement'!E33 -> -1522.4 | F32: =-'Income statement'!F7*'Cash Flow statement'!F33 -> -1590.908 | G32: =-'Income statement'!G7*'Cash Flow statement'!G33 -> -1662.4989 | H32: =-'Income statement'!H7*'Cash Flow statement'!H33 -> -1737.3113 | I32: =-'Income statement'!I7*'Cash Flow statement'!I33 -> -1815.4903
A33: CAPEX as % of sales | B33: =-B32/'Income statement'!B7 -> 0.04517689 | C33: =-C32/'Income statement'!C7 -> 0.043062901 | D33: =-D32/'Income statement'!D7 -> 0.034561663 | E33: 0.0346 | F33: 0.0346 | G33: 0.0346 | H33: 0.0346 | I33: 0.0346
A34: Divestiture of training services business | D34: 333 | E34: 0 | F34: 0 | G34: 0 | H34: 0 | I34: 0
A35: Proceeds from sale of minority investments | B35: 197 | E35: 0 | F35: 0 | G35: 0 | H35: 0 | I35: 0
A36: Other investing activities | B36: -4 | C36: 18 | D36: -38 | E36: 0 | F36: 0 | G36: 0 | H36: 0 | I36: 0
A37: Net cash used in investing activities | B37: =B32+B34+B35+B36 -> -1582 | C37: =C32+C34+C35+C36 -> -1749 | D37: =D32+D34+D35+D36 -> -1155 | E37: =E32+E34+E35+E36 -> -1522.4 | F37: =F32+F34+F35+F36 -> -1590.908 | G37: =G32+G34+G35+G36 -> -1662.4989 | H37: =H32+H34+H35+H36 -> -1737.3113 | I37: =I32+I34+I35+I36 -> -1815.4903
A39: Financing activities:
A40: Net proceeds from issuing long-term debt | B40: 1995 | C40: 2495 | D40: 998 | E40: 0 | F40: 0 | G40: 0 | H40: 0 | I40: 0
A41: Payments of long-term debt | B41: -1050 | D41: -1500
A42: Common stock repurchase | B42: -1500 | C42: -2514 | D42: -1624 | E42: -1500 | F42: -1500 | G42: -1500 | H42: -1500 | I42: -1500
A43: cash dividends paid | B43: -1116 | C43: -1186 | D43: -1293 | E43: =-1*'Income statement'!E53*'Cash Flow statement'!E44 -> -1409.4907 | F43: =-1*'Income statement'!F53*'Cash Flow statement'!F44 -> -1559.7094 | G43: =-1*'Income statement'!G53*'Cash Flow statement'!G44 -> -1725.9378 | H43: =-1*'Income statement'!H53*'Cash Flow statement'!H44 -> -1909.8823 | I43: =-1*'Income statement'!I53*'Cash Flow statement'!I44 -> -2113.4309
A44: Dividend per share | B44: =-B43/'Income statement'!B53 -> 7.3421053 | C44: =-C43/'Income statement'!C53 -> 8.0515954 | D44: =-D43/'Income statement'!D53 -> 8.9916551 | E44: =D44*(1+$B$58) -> 9.9510086 | F44: =E44*(1+$B$58) -> 11.012719 | G44: =F44*(1+$B$58) -> 12.187708 | H44: =G44*(1+$B$58) -> 13.48806 | I44: =H44*(1+$B$58) -> 14.927152
A45: Payments of employee taxes withheld from share-based awards | B45: -52 | C45: -58 | D45: -39 | E45: 0 | F45: 0 | G45: 0 | H45: 0 | I45: 0
A46: Other financing activites | B46: -38 | C46: -132 | D46: -94
A47: Net cash provided by (used in) financing activities | B47: =B40+B41+B42+B43+B45+B46 -> -1761 | C47: =C40+C41+C42+C43+C45+C46 -> -1395 | D47: =D40+D41+D42+D43+D45+D46 -> -3552 | E47: =E40+E41+E42+E43+E45+E46 -> -2909.4907 | F47: =F40+F41+F42+F43+F45+F46 -> -3059.7094 | G47: =G40+G41+G42+G43+G45+G46 -> -3225.9378 | H47: =H40+H41+H42+H43+H45+H46 -> -3409.8823 | I47: =I40+I41+I42+I43+I45+I46 -> -3613.4309
A49: Increase in cash and equivalents | B49: =B29+B37+B47 -> 532 | C49: =C29+C37+C47 -> 1244 | D49: =D29+D37+D47 -> 50 | E49: =E29+E37+E47 -> 338.41123 | F49: =F29+F37+F47 -> 27.156273 | G49: =G29+G37+G47 -> 20.627721 | H49: =H29+H37+H47 -> 3.5696296 | I49: =I29+I37+I47 -> -25.582716
A50: Cash and cash equivalents, beginning of year | B50: 2577 | C50: 3109 | D50: 4353 | E50: 4403 | F50: 7777 | G50: 11294 | H50: 14959 | I50: 18779
A51: Ending cash balance | B51: =B49+B50 -> 3109 | C51: =C49+C50 -> 4353 | D51: =D49+D50 -> 4403 | E51: =E49+E50 -> 4741.4112 | F51: =F49+F50 -> 7804.1563 | G51: =G49+G50 -> 11314.628 | H51: =H49+H50 -> 14962.57 | I51: =I49+I50 -> 18753.417
A55: Dividend growth rate
A56: 2024 | B56: =(C44/B44)-1 -> 0.096633063
A57: 2025 | B57: =(D44/C44)-1 -> 0.11675446
B58: =AVERAGE(B56:B57) -> 0.10669376
A59: Found the growth rate of DPS then took the average (to get 10.67%). This average was then applied to 2026 based upon the 2025 DPS value
A60: With the cash dividends paid you are essentially saying the number of diluted shares outstanding times the DPS value is going to be what you pay out to shareholders. As it is based upon the average growth rate of dividends

Sheet Balance sheet
A1: NORTHROP GRUMMAN CORPORATION
A2: CONSOLIDATED STATEMENTS OF FINANCIAL POSITION
A3: $ in millions
B4: 2023 | C4: 2024 | D4: 2025 | E4: =D4+1 -> 2026 | F4: =E4+1 -> 2027 | G4: =F4+1 -> 2028 | H4: =G4+1 -> 2029 | I4: =H4+1 -> 2030
A5: Check: | B5: =B23-B45 -> 0 | C5: =C23-C45 -> 0 | D5: =D23-D45 -> 0 | E5: =E23-E45 -> -18.460658 | F5: =F23-F45 -> 1026.611 | G5: =G23-G45 -> 2526.1393 | H5: =H23-H45 -> 4180.407 | I5: =I23-I45 -> 6006.9531
A6: Assets
A7: Current assets
A8: Cash & cash equivalents | B8: 3109 | C8: 4353 | D8: 4403 | E8: ='Cash Flow statement'!E51 -> 4741.4112 | F8: ='Cash Flow statement'!F51 -> 7804.1563 | G8: ='Cash Flow statement'!G51 -> 11314.628 | H8: ='Cash Flow statement'!H51 -> 14962.57 | I8: ='Cash Flow statement'!I51 -> 18753.417
A9: Accounts receivable | B9: 1454 | C9: 1272 | D9: 1375 | E9: =('Income statement'!E7*'Balance sheet'!E10)/365 -> 1478.1111 | F9: =('Income statement'!F7*'Balance sheet'!F10)/365 -> 1544.6261 | G9: =('Income statement'!G7*'Balance sheet'!G10)/365 -> 1614.1343 | H9: =('Income statement'!H7*'Balance sheet'!H10)/365 -> 1686.7703 | I9: =('Income statement'!I7*'Balance sheet'!I10)/365 -> 1762.675
A10: Day sales outstanding (DSO) | B10: ='Working capital schedule'!B8 -> 13.507508 | C10: ='Working capital schedule'!C8 -> 11.314795 | D10: ='Working capital schedule'!D8 -> 11.962507 | E10: ='Working capital schedule'!E8 -> 12.261603 | F10: ='Working capital schedule'!F8 -> 12.261603 | G10: ='Working capital schedule'!G8 -> 12.261603 | H10: ='Working capital schedule'!H8 -> 12.261603 | I10: ='Working capital schedule'!I8 -> 12.261603
A11: Unbilled receivables | B11: 5693 | C11: 5908 | D11: 6544 | E11: ='Income statement'!E7*'Working capital schedule'!E10 -> 6524.598 | F11: ='Income statement'!F7*'Working capital schedule'!F10 -> 6818.2049 | G11: ='Income statement'!G7*'Working capital schedule'!G10 -> 7125.0241 | H11: ='Income statement'!H7*'Working capital schedule'!H10 -> 7445.6502 | I11: ='Income statement'!I7*'Working capital schedule'!I10 -> 7780.7045
A12: Inventories | B12: 1109 | C12: 1455 | D12: 1309 | E12: ='Income statement'!E7*'Working capital schedule'!E6 -> 1391.663 | F12: ='Income statement'!F7*'Working capital schedule'!F6 -> 1454.2879 | G12: ='Income statement'!G7*'Working capital schedule'!G6 -> 1519.7308 | H12: ='Income statement'!H7*'Working capital schedule'!H6 -> 1588.1187 | I12: ='Income statement'!I7*'Working capital schedule'!I6 -> 1659.584
A13: Prepaid expenses & other current assets | B13: 2341 | C13: 1286 | D13: 1656 | E13: ='Income statement'!E7*'Working capital schedule'!E12 -> 1912.4603 | F13: ='Income statement'!F7*'Working capital schedule'!F12 -> 1998.521 | G13: ='Income statement'!G7*'Working capital schedule'!G12 -> 2088.4545 | H13: ='Income statement'!H7*'Working capital schedule'!H12 -> 2182.4349 | I13: ='Income statement'!I7*'Working capital schedule'!I12 -> 2280.6445
A14: Total current assets | B14: =B8+B9+B11+B12+B13 -> 13706 | C14: =C8+C9+C11+C12+C13 -> 14274 | D14: =D8+D9+D11+D12+D13 -> 15287 | E14: =E8+E9+E11+E12+E13 -> 16048.244 | F14: =F8+F9+F11+F12+F13 -> 19619.796 | G14: =G8+G9+G11+G12+G13 -> 23661.971 | H14: =H8+H9+H11+H12+H13 -> 27865.544 | I14: =I8+I9+I11+I12+I13 -> 32237.025
A16: Non-current assets
A17: Property, plant, & equipment | B17: 9653 | C17: 10536 | D17: 10972 | E17: ='PPE schedule'!E14 -> 11815.071 | F17: ='PPE schedule'!F14 -> 11725.189 | G17: ='PPE schedule'!G14 -> 11593.558 | H17: ='PPE schedule'!H14 -> 11418.298 | I17: ='PPE schedule'!I14 -> 11197.446
A18: Operating lease right-of-use assets | B18: 1818 | C18: 1770 | D18: 1859 | E18: =D18 -> 1859 | F18: =E18 -> 1859 | G18: =F18 -> 1859 | H18: =G18 -> 1859 | I18: =H18 -> 1859
A19: Goodwill | B19: 17517 | C19: 17512 | D19: 17437 | E19: =D19 -> 17437 | F19: =E19 -> 17437 | G19: =F19 -> 17437 | H19: =G19 -> 17437 | I19: =H19 -> 17437
A20: Deferred tax assets | B20: 1020 | C20: 1599 | D20: 1051 | E20: =D20 -> 1051 | F20: =E20 -> 1051 | G20: =F20 -> 1051 | H20: =G20 -> 1051 | I20: =H20 -> 1051
A21: Pension & other postretirement benefit plan assets | B21: 1331 | C21: 2184 | D21: 3167 | E21: =D21 -> 3167 | F21: =E21 -> 3167 | G21: =F21 -> 3167 | H21: =G21 -> 3167 | I21: =H21 -> 3167
A22: Other assets | B22: 1499 | C22: 1484 | D22: 1604 | E22: =D22 -> 1604 | F22: =E22 -> 1604 | G22: =F22 -> 1604 | H22: =G22 -> 1604 | I22: =H22 -> 1604
A23: Total assets | B23: =B14+B17+B18+B19+B20+B21+B22 -> 46544 | C23: =C14+C17+C18+C19+C20+C21+C22 -> 49359 | D23: =D14+D17+D18+D19+D20+D21+D22 -> 51377 | E23: =E14+E17+E18+E19+E20+E21+E22 -> 52981.314 | F23: =F14+F17+F18+F19+F20+F21+F22 -> 56462.986 | G23: =G14+G17+G18+G19+G20+G21+G22 -> 60373.53 | H23: =H14+H17+H18+H19+H20+H21+H22 -> 64401.842 | I23: =I14+I17+I18+I19+I20+I21+I22 -> 68552.472
A25: Liabilities
A26: Accounts payable | B26: 2110 | C26: 2599 | D26: 3240 | E26: =('Income statement'!E11*'Working capital schedule'!E17)/365 -> 2856.3783 | F26: =('Income statement'!F11*'Working capital schedule'!F17)/365 -> 2984.9153 | G26: =('Income statement'!G11*'Working capital schedule'!G17)/365 -> 3119.2365 | H26: =('Income statement'!H11*'Working capital schedule'!H17)/365 -> 3259.6022 | I26: =('Income statement'!I11*'Working capital schedule'!I17)/365 -> 3406.2843
A27: Accrued employee compensation | B27: 2251 | C27: 2271 | D27: 2309 | E27: ='Income statement'!E7*'Working capital schedule'!E19 -> 2421.6046 | F27: ='Income statement'!F7*'Working capital schedule'!F19 -> 2530.5768 | G27: ='Income statement'!G7*'Working capital schedule'!G19 -> 2644.4528 | H27: ='Income statement'!H7*'Working capital schedule'!H19 -> 2763.4532 | I27: ='Income statement'!I7*'Working capital schedule'!I19 -> 2887.8085
A28: Advance payments & billings in excess of costs incurred | B28: 4193 | C28: 4070 | D28: 4086 | E28: ='Income statement'!E7*'Working capital schedule'!E21 -> 4448.4016 | F28: ='Income statement'!F7*'Working capital schedule'!F21 -> 4648.5796 | G28: ='Income statement'!G7*'Working capital schedule'!G21 -> 4857.7657 | H28: ='Income statement'!H7*'Working capital schedule'!H21 -> 5076.3652 | I28: ='Income statement'!I7*'Working capital schedule'!I21 -> 5304.8016
A29: Other current liabilities | B29: 3388 | C29: 5188 | D29: 4247 | E29: =D29 -> 4247 | F29: =E29 -> 4247 | G29: =F29 -> 4247 | H29: =G29 -> 4247 | I29: =H29 -> 4247
A30: Total current liabilities | B30: =B26+B27+B28+B29 -> 11942 | C30: =C26+C27+C28+C29 -> 14128 | D30: =D26+D27+D28+D29 -> 13882 | E30: =E26+E27+E28+E29 -> 13973.384 | F30: =F26+F27+F28+F29 -> 14411.072 | G30: =G26+G27+G28+G29 -> 14868.455 | H30: =H26+H27+H28+H29 -> 15346.42 | I30: =I26+I27+I28+I29 -> 15845.894
A32: Long-term liabilities
A33: Long-term debt | B33: 13786 | C33: 14692 | D33: 15162 | E33: ='Debt schedule'!E8 -> 14660 | F33: ='Debt schedule'!F8 -> 14660 | G33: ='Debt schedule'!G8 -> 14660 | H33: ='Debt schedule'!H8 -> 14660 | I33: ='Debt schedule'!I8 -> 14660
A34: Pension & other postretirement liabilities | B34: 1290 | C34: 1120 | D34: 1110 | E34: =D34 -> 1110 | F34: =E34 -> 1110 | G34: =F34 -> 1110 | H34: =G34 -> 1110 | I34: =H34 -> 1110
A35: Operating lease liabilities | B35: 1892 | C35: 1798 | D35: 1857 | E35: =D35 -> 1857 | F35: =E35 -> 1857 | G35: =F35 -> 1857 | H35: =G35 -> 1857 | I35: =H35 -> 1857
A36: Other long-term liabilities | B36: 2839 | C36: 2331 | D36: 2692 | E36: =D36 -> 2692 | F36: =E36 -> 2692 | G36: =F36 -> 2692 | H36: =G36 -> 2692 | I36: =H36 -> 2692
A37: Total liabilities | B37: =B30+B33+B34+B35+B36 -> 31749 | C37: =C30+C33+C34+C35+C36 -> 34069 | D37: =D30+D33+D34+D35+D36 -> 34703 | E37: =E30+E33+E34+E35+E36 -> 34292.384 | F37: =F30+F33+F34+F35+F36 -> 34730.072 | G37: =G30+G33+G34+G35+G36 -> 35187.455 | H37: =H30+H33+H34+H35+H36 -> 35665.42 | I37: =I30+I33+I34+I35+I36 -> 36164.894
A39: Shareholders' equity
A40: Common stock | B40: 150 | C40: 145 | D40: 142 | E40: =D40 -> 142 | F40: =E40 -> 142 | G40: =F40 -> 142 | H40: =G40 -> 142 | I40: =H40 -> 142
A41: Retained earnings | B41: 14773 | C41: 15297 | D41: 16658 | E41: =D41+'Cash Flow statement'!E7+('Cash Flow statement'!E43) -> 18691.391 | F41: =E41+'Cash Flow statement'!F7+('Cash Flow statement'!F43) -> 20690.303 | G41: =F41+'Cash Flow statement'!G7+('Cash Flow statement'!G43) -> 22643.935 | H41: =G41+'Cash Flow statement'!H7+('Cash Flow statement'!H43) -> 24540.015 | I41: =H41+'Cash Flow statement'!I7+('Cash Flow statement'!I43) -> 26364.624
A42: Accumulated other comprehensive income | B42: -128 | C42: -152 | D42: -126 | E42: =D42 -> -126 | F42: =E42 -> -126 | G42: =F42 -> -126 | H42: =G42 -> -126 | I42: =H42 -> -126
A43: Total shareholders' equity | B43: =B40+B41+B42 -> 14795 | C43: =C40+C41+C42 -> 15290 | D43: =D40+D41+D42 -> 16674 | E43: =E40+E41+E42 -> 18707.391 | F43: =F40+F41+F42 -> 20706.303 | G43: =G40+G41+G42 -> 22659.935 | H43: =H40+H41+H42 -> 24556.015 | I43: =I40+I41+I42 -> 26380.624
A45: Total liabilities and shareholders' equity | B45: =B37+B43 -> 46544 | C45: =C37+C43 -> 49359 | D45: =D37+D43 -> 51377 | E45: =E37+E43 -> 52999.775 | F45: =F37+F43 -> 55436.375 | G45: =G37+G43 -> 57847.39 | H45: =H37+H43 -> 60221.435 | I45: =I37+I43 -> 62545.519
A55: Other equity reserves | E55: -1022 | F55: 1556 | G55: 1518 | H55: 1672 | I55: 1845

Sheet Supporting schedules -->

Sheet PPE schedule
A1: PP & E SCHEDULE ($, Millions)
B2: 2023 | C2: 2024 | D2: 2025 | E2: =2025+1 -> 2026 | F2: =E2+1 -> 2027 | G2: =F2+1 -> 2028 | H2: =G2+1 -> 2029 | I2: =H2+1 -> 2030
A4: Gross PP&E (Beginning balance) | C4: 19269 | D4: 20620 | E4: =D8 -> 22070 | F4: =E8 -> 23592.4 | G4: =F8 -> 25183.308 | H4: =G8 -> 26845.807 | I4: =H8 -> 28583.118
A5: Capital expenditures (CapEx) | C5: =-1*'Cash Flow statement'!C32 -> 1767 | D5: =-1*'Cash Flow statement'!D32 -> 1450 | E5: =-1*'Cash Flow statement'!E32 -> 1522.4 | F5: =-1*'Cash Flow statement'!F32 -> 1590.908 | G5: =-1*'Cash Flow statement'!G32 -> 1662.4989 | H5: =-1*'Cash Flow statement'!H32 -> 1737.3113 | I5: =-1*'Cash Flow statement'!I32 -> 1815.4903
A6: Depreciation as a % of gross PP&E | C6: ='Income statement'!C22/C4 -> 0.071098656 | D6: ='Income statement'!D22/D4 -> 0.071387003 | E6: =AVERAGE($C$6:$D$6) -> 0.071242829 | F6: =AVERAGE($C$6:$D$6) -> 0.071242829 | G6: =AVERAGE($C$6:$D$6) -> 0.071242829 | H6: =AVERAGE($C$6:$D$6) -> 0.071242829 | I6: =AVERAGE($C$6:$D$6) -> 0.071242829
A7: Retirements/Disposals | C7: 0 | D7: 0 | E7: 0 | F7: 0 | G7: 0 | H7: 0 | I7: 0
A8: Gross PP&E (Ending balance) | C8: =C4+C5-C7 -> 21036 | D8: =D4+D5-D7 -> 22070 | E8: =E4+E5-E7 -> 23592.4 | F8: =F4+F5-F7 -> 25183.308 | G8: =G4+G5-G7 -> 26845.807 | H8: =H4+H5-H7 -> 28583.118 | I8: =I4+I5-I7 -> 30398.608
A10: Accumulated depreciation (Beginning balance) | C10: 7964 | D10: 8733 | E10: =D13 -> 10205 | F10: =E13 -> 11777.329 | G10: =F13 -> 13458.119 | H10: =G13 -> 15252.249 | I10: =H13 -> 17164.82
A11: Depreciation expense | C11: ='Income statement'!C22 -> 1370 | D11: ='Income statement'!D22 -> 1472 | E11: =E4*E6 -> 1572.3292 | F11: =F4*F6 -> 1680.7893 | G11: =G4*G6 -> 1794.1301 | H11: =H4*H6 -> 1912.5712 | I11: =I4*I6 -> 2036.3422
A12: Retirements/Disposals | C12: 0 | D12: 0
A13: Accumulated depreciation (Ending balance) | C13: =C10+C11-C12 -> 9334 | D13: =D10+D11-D12 -> 10205 | E13: =E10+E11-E12 -> 11777.329 | F13: =F10+F11-F12 -> 13458.119 | G13: =G10+G11-G12 -> 15252.249 | H13: =H10+H11-H12 -> 17164.82 | I13: =I10+I11-I12 -> 19201.162
A14: Net PP&E (Ending balance) | C14: =C8-C13 -> 11702 | D14: =D8-D13 -> 11865 | E14: =D14+E5-E11 -> 11815.071 | F14: =E14+F5-F11 -> 11725.189 | G14: =F14+G5-G11 -> 11593.558 | H14: =G14+H5-H11 -> 11418.298 | I14: =H14+I5-I11 -> 11197.446

Sheet Working capital schedule
A1: OPERATING WORKING CAPITAL SCHEDULE ($, Millions)
B2: 2023 | C2: 2024 | D2: 2025 | E2: =D2+1 -> 2026 | F2: =E2+1 -> 2027 | G2: =F2+1 -> 2028 | H2: =G2+1 -> 2029 | I2: =H2+1 -> 2030
A4: Current assets
A5: Inventory | B5: ='Balance sheet'!B12 -> 1109 | C5: ='Balance sheet'!C12 -> 1455 | D5: ='Balance sheet'!D12 -> 1309 | E5: ='Income statement'!E7*'Working capital schedule'!E6 -> 1391.663 | F5: ='Income statement'!F7*'Working capital schedule'!F6 -> 1454.2879 | G5: ='Income statement'!G7*'Working capital schedule'!G6 -> 1519.7308 | H5: ='Income statement'!H7*'Working capital schedule'!H6 -> 1588.1187 | I5: ='Income statement'!I7*'Working capital schedule'!I6 -> 1659.584
A6: Inventory as a % of sales | B6: =B5/'Income statement'!B7 -> 0.028226012 | C6: =C5/'Income statement'!C7 -> 0.035459264 | D6: =D5/'Income statement'!D7 -> 0.031200839 | E6: =AVERAGE($B$6:$D$6) -> 0.031628705 | F6: =AVERAGE($B$6:$D$6) -> 0.031628705 | G6: =AVERAGE($B$6:$D$6) -> 0.031628705 | H6: =AVERAGE($B$6:$D$6) -> 0.031628705 | I6: =AVERAGE($B$6:$D$6) -> 0.031628705
A7: Accounts receivable | B7: ='Balance sheet'!B9 -> 1454 | C7: ='Balance sheet'!C9 -> 1272 | D7: ='Balance sheet'!D9 -> 1375 | E7: =E8/356*'Income statement'!E7 -> 1515.4791 | F7: =F8/356*'Income statement'!F7 -> 1583.6756 | G7: =G8/356*'Income statement'!G7 -> 1654.941 | H7: =H8/356*'Income statement'!H7 -> 1729.4134 | I7: =I8/356*'Income statement'!I7 -> 1807.237
A8: Accounts receivable days | B8: =B7/'Income statement'!B7*365 -> 13.507508 | C8: =C7/'Income statement'!C7*365 -> 11.314795 | D8: =D7/'Income statement'!D7*365 -> 11.962507 | E8: =AVERAGE($B$8:$D$8) -> 12.261603 | F8: =AVERAGE($B$8:$D$8) -> 12.261603 | G8: =AVERAGE($B$8:$D$8) -> 12.261603 | H8: =AVERAGE($B$8:$D$8) -> 12.261603 | I8: =AVERAGE($B$8:$D$8) -> 12.261603
A9: Unbilled receivables | B9: ='Balance sheet'!B11 -> 5693 | C9: ='Balance sheet'!C11 -> 5908 | D9: ='Balance sheet'!D11 -> 6544 | E9: ='Income statement'!E7*'Working capital schedule'!E10 -> 6524.598 | F9: ='Income statement'!F7*'Working capital schedule'!F10 -> 6818.2049 | G9: ='Income statement'!G7*'Working capital schedule'!G10 -> 7125.0241 | H9: ='Income statement'!H7*'Working capital schedule'!H10 -> 7445.6502 | I9: ='Income statement'!I7*'Working capital schedule'!I10 -> 7780.7045
A10: Unbilled receivables as a % of revenue | B10: =B9/'Income statement'!B7 -> 0.14489692 | C10: =C9/'Income statement'!C7 -> 0.14398167 | D10: =D9/'Income statement'!D7 -> 0.15598036 | E10: =AVERAGE($B$10:$D$10) -> 0.14828632 | F10: =AVERAGE($B$10:$D$10) -> 0.14828632 | G10: =AVERAGE($B$10:$D$10) -> 0.14828632 | H10: =AVERAGE($B$10:$D$10) -> 0.14828632 | I10: =AVERAGE($B$10:$D$10) -> 0.14828632
A11: Prepaid expenses and other assets | B11: ='Balance sheet'!B13 -> 2341 | C11: ='Balance sheet'!C13 -> 1286 | D11: ='Balance sheet'!D13 -> 1656 | E11: =E12*'Income statement'!E7 -> 1912.4603 | F11: =F12*'Income statement'!F7 -> 1998.521 | G11: =G12*'Income statement'!G7 -> 2088.4545 | H11: =H12*'Income statement'!H7 -> 2182.4349 | I11: =I12*'Income statement'!I7 -> 2280.6445
A12: Prepaid expenses and other assets as a % of revenue | B12: =B11/'Income statement'!B7 -> 0.059582591 | C12: =C11/'Income statement'!C7 -> 0.031340628 | D12: =D11/'Income statement'!D7 -> 0.039471802 | E12: =AVERAGE($B$12:$D$12) -> 0.043465007 | F12: =AVERAGE($B$12:$D$12) -> 0.043465007 | G12: =AVERAGE($B$12:$D$12) -> 0.043465007 | H12: =AVERAGE($B$12:$D$12) -> 0.043465007 | I12: =AVERAGE($B$12:$D$12) -> 0.043465007
A13: Total current assets | B13: =B5+B7+B9+B11 -> 10597 | C13: =C5+C7+C9+C11 -> 9921 | D13: =D5+D7+D9+D11 -> 10884 | E13: =E5+E7+E9+E11 -> 11344.2 | F13: =F5+F7+F9+F11 -> 11854.689 | G13: =G5+G7+G9+G11 -> 12388.15 | H13: =H5+H7+H9+H11 -> 12945.617 | I13: =I5+I7+I9+I11 -> 13528.17
A15: Current liabilities
A16: Accounts payable | B16: ='Balance sheet'!B26 -> 2110 | C16: ='Balance sheet'!C26 -> 2599 | D16: ='Balance sheet'!D26 -> 3240 | E16: =E17/365*'Income statement'!E11 -> 2856.3783 | F16: =F17/365*'Income statement'!F11 -> 2984.9153 | G16: =G17/365*'Income statement'!G11 -> 3119.2365 | H16: =H17/365*'Income statement'!H11 -> 3259.6022 | I16: =I17/365*'Income statement'!I11 -> 3406.2843
A17: Days payable outstanding | B17: =B16/'Income statement'!B11*365 -> 24.406592 | C17: =C16/'Income statement'!C11*365 -> 30.121134 | D17: =D16/'Income statement'!D11*365 -> 36.458365 | E17: =AVERAGE($B$17:$D$17) -> 30.328697 | F17: =AVERAGE($B$17:$D$17) -> 30.328697 | G17: =AVERAGE($B$17:$D$17) -> 30.328697 | H17: =AVERAGE($B$17:$D$17) -> 30.328697 | I17: =AVERAGE($B$17:$D$17) -> 30.328697
A18: Accrued expenses | B18: ='Balance sheet'!B27 -> 2251 | C18: ='Balance sheet'!C27 -> 2271 | D18: ='Balance sheet'!D27 -> 2309 | E18: ='Income statement'!E7*'Working capital schedule'!E19 -> 2421.6046 | F18: ='Income statement'!F7*'Working capital schedule'!F19 -> 2530.5768 | G18: ='Income statement'!G7*'Working capital schedule'!G19 -> 2644.4528 | H18: ='Income statement'!H7*'Working capital schedule'!H19 -> 2763.4532 | I18: ='Income statement'!I7*'Working capital schedule'!I19 -> 2887.8085
A19: Accrued compensation as a % of revenue | B19: =B18/'Income statement'!B7 -> 0.057291932 | C19: =C18/'Income statement'!C7 -> 0.055345697 | D19: =D18/'Income statement'!D7 -> 0.055036469 | E19: =D19 -> 0.055036469 | F19: =E19 -> 0.055036469 | G19: =F19 -> 0.055036469 | H19: =G19 -> 0.055036469 | I19: =H19 -> 0.055036469
A20: Unearned revenue | B20: ='Balance sheet'!B28 -> 4193 | C20: ='Balance sheet'!C28 -> 4070 | D20: ='Balance sheet'!D28 -> 4086 | E20: ='Income statement'!E7*'Working capital schedule'!E21 -> 4448.4016 | F20: ='Income statement'!F7*'Working capital schedule'!F21 -> 4648.5796 | G20: ='Income statement'!G7*'Working capital schedule'!G21 -> 4857.7657 | H20: ='Income statement'!H7*'Working capital schedule'!H21 -> 5076.3652 | I20: ='Income statement'!I7*'Working capital schedule'!I21 -> 5304.8016
A21: Unearned revenue as a % of total revenue | B21: =B20/'Income statement'!B7 -> 0.10671927 | C21: =C20/'Income statement'!C7 -> 0.099188458 | D21: =D20/'Income statement'!D7 -> 0.097392382 | E21: =AVERAGE($B$21:$D$21) -> 0.10110004 | F21: =AVERAGE($B$21:$D$21) -> 0.10110004 | G21: =AVERAGE($B$21:$D$21) -> 0.10110004 | H21: =AVERAGE($B$21:$D$21) -> 0.10110004 | I21: =AVERAGE($B$21:$D$21) -> 0.10110004
A22: Income taxes payable | B22: ='Cash Flow statement'!B27 -> -658 | C22: ='Cash Flow statement'!C27 -> 1143 | D22: ='Cash Flow statement'!D27 -> -559 | E22: =AVERAGE($B$22:$D$22) -> -24.666667 | F22: =AVERAGE($B$22:$D$22) -> -24.666667 | G22: =AVERAGE($B$22:$D$22) -> -24.666667 | H22: =AVERAGE($B$22:$D$22) -> -24.666667 | I22: =AVERAGE($B$22:$D$22) -> -24.666667
A23: Income taxes payable as a % of tax expense | B23: =B22/'Income statement'!B41 -> -2.2689655 | C23: =C22/'Income statement'!C41 -> 1.3574822 | D23: =D22/'Income statement'!D41 -> -0.63092551 | E23: =E22/'Income statement'!E41 -> -0.034979821 | F23: =F22/'Income statement'!F41 -> -0.03384214 | G23: =G22/'Income statement'!G41 -> -0.032729739 | H23: =H22/'Income statement'!H41 -> -0.031642824 | I23: =I22/'Income statement'!I41 -> -0.030581547
A24: Other liabilities | B24: =1000 -> 1000 | C24: =B24+'Cash Flow statement'!C26 -> 125 | D24: =C24+'Cash Flow statement'!D26 -> -87 | E24: 0 | F24: 0 | G24: 0 | H24: 0 | I24: 0
A25: Total current liabilities | B25: =B16+B18+B20 -> 8554 | C25: =C16+C18+C20 -> 8940 | D25: =D16+D18+D20 -> 9635 | E25: =E16+E18+E20 -> 9726.3845 | F25: =F16+F18+F20 -> 10164.072 | G25: =G16+G18+G20 -> 10621.455 | H25: =H16+H18+H20 -> 11099.42 | I25: =I16+I18+I20 -> 11598.894
A26: Net working capital (NWC) | B26: =B13-B25 -> 2043 | C26: =C13-C25 -> 981 | D26: =D13-D25 -> 1249 | E26: =E13-E25 -> 1617.8159 | F26: =F13-F25 -> 1690.6176 | G26: =G13-G25 -> 1766.6954 | H26: =H13-H25 -> 1846.1967 | I26: =I13-I25 -> 1929.2756

Sheet Debt schedule
A1: DEBT SCHEDULE ($, Millions)
B2: 2023 | C2: 2024 | D2: 2025 | E2: =D2+1 -> 2026 | F2: =E2+1 -> 2027 | G2: =F2+1 -> 2028 | H2: =G2+1 -> 2029 | I2: =H2+1 -> 2030
A4: Long - term debt (Beginning balance) | B4: ='Balance sheet'!B33 -> 13786 | C4: ='Balance sheet'!C33 -> 14692 | D4: ='Balance sheet'!D33 -> 15162 | E4: =D8 -> 14660 | F4: =E8 -> 14660 | G4: =F8 -> 14660 | H4: =G8 -> 14660 | I4: =H8 -> 14660
A5: Plus: New debt issuance | B5: ='Cash Flow statement'!B40 -> 1995 | C5: ='Cash Flow statement'!C40 -> 2495 | D5: ='Cash Flow statement'!D40 -> 998 | E5: ='Cash Flow statement'!E40 -> 0 | F5: 0 | G5: 0 | H5: 0 | I5: 0
A6: Less: Debt repayments/maturities | B6: =-1*'Cash Flow statement'!B41 -> 1050 | C6: =-1*'Cash Flow statement'!C41 -> 0 | D6: =-1*'Cash Flow statement'!D41 -> 1500 | E6: ='Cash Flow statement'!E41 -> 0 | F6: ='Cash Flow statement'!F41 -> 0 | G6: ='Cash Flow statement'!G41 -> 0 | H6: ='Cash Flow statement'!H41 -> 0 | I6: ='Cash Flow statement'!I41 -> 0
A7: Reclassification of short - term debt | B7: 0 | C7: 2025 | D7: 0
A8: Long - term debt (Ending balance) | B8: =B4+B5-B6-B7 -> 14731 | C8: =C4+C5-C6-C7 -> 15162 | D8: =D4+D5-D6-D7 -> 14660 | E8: =E4+E5-E6 -> 14660 | F8: =F4+F5-F6 -> 14660 | G8: =G4+G5-G6 -> 14660 | H8: =H4+H5-H6 -> 14660 | I8: =I4+I5-I6 -> 14660
A9: Average debt outstanding | B9: =AVERAGE(B8,B4) -> 14258.5 | C9: =AVERAGE(C8,C4) -> 14927 | D9: =AVERAGE(D8,D4) -> 14911 | E9: =AVERAGE(E8,E4) -> 14660 | F9: =AVERAGE(F8,F4) -> 14660 | G9: =AVERAGE(G8,G4) -> 14660 | H9: =AVERAGE(H8,H4) -> 14660 | I9: =AVERAGE(I8,I4) -> 14660
A10: Weighted average interest rate (%) | B10: =-1*'Income statement'!B30/'Debt schedule'!B4 -> 0.039532859 | C10: =-1*'Income statement'!C30/'Debt schedule'!C4 -> 0.042267901 | D10: =-1*'Income statement'!D30/'Debt schedule'!D4 -> 0.043859649 | E10: =D10 -> 0.043859649 | F10: =E10 -> 0.043859649 | G10: =F10 -> 0.043859649 | H10: =G10 -> 0.043859649 | I10: =H10 -> 0.043859649
A11: Calculated interest expense | B11: =B9*B10 -> 563.67928 | C11: =C9*C10 -> 630.93296 | D11: =D9*D10 -> 653.99123 | E11: =E9*E10 -> 642.98246 | F11: =F9*F10 -> 642.98246 | G11: =G9*G10 -> 642.98246 | H11: =H9*H10 -> 642.98246 | I11: =I9*I10 -> 642.98246

Sheet Valuation -->
A1: COMPANY VALUATION ANALYSIS: NORTHRUP GRUMMAN
T20: Working capital:
T21: accounts receivable + inventory - (accounts payable + accrued expenses)
T23: Net debt:
T24: short term liabilities + long term debt - cash & cash equivalents

Sheet DCF
A1: DISCOUNTED CASH FLOW VALUATION MODEL ($, IN MILLIONS)
E2: =2026 -> 2026 | F2: =E2+1 -> 2027 | G2: =F2+1 -> 2028 | H2: =G2+1 -> 2029 | I2: =H2+1 -> 2030
A3: EBIT | E3: ='Income statement'!E24 -> 3936.6989 | F3: ='Income statement'!F24 -> 4076.145 | G3: ='Income statement'!G24 -> 4221.8663 | H3: ='Income statement'!H24 -> 4374.145 | I3: ='Income statement'!I24 -> 4533.2763
A4: Less: Taxes (@17%) | E4: =E3*'Income statement'!E42 -> 669.23881 | F4: =F3*'Income statement'!F42 -> 692.94466 | G4: =G3*'Income statement'!G42 -> 717.71727 | H4: =H3*'Income statement'!H42 -> 743.60465 | I4: =I3*'Income statement'!I42 -> 770.65697
A5: NOPAT | E5: =E3-E4 -> 3267.4601 | F5: =F3-F4 -> 3383.2004 | G5: =G3-G4 -> 3504.149 | H5: =H3-H4 -> 3630.5404 | I5: =I3-I4 -> 3762.6193
A6: Add: Depreciation & Amortization | E6: ='Cash Flow statement'!E10 -> 1572.3292 | F6: ='Cash Flow statement'!F10 -> 1680.7893 | G6: ='Cash Flow statement'!G10 -> 1794.1301 | H6: ='Cash Flow statement'!H10 -> 1912.5712 | I6: ='Cash Flow statement'!I10 -> 2036.3422
E7: =E5+E6 -> 4839.7893 | F7: =F5+F6 -> 5063.9897 | G7: =G5+G6 -> 5298.2792 | H7: =H5+H6 -> 5543.1116 | I7: =I5+I6 -> 5798.9615
A8: Less: CapEx | E8: ='Cash Flow statement'!E32 -> -1522.4 | F8: ='Cash Flow statement'!F32 -> -1590.908 | G8: ='Cash Flow statement'!G32 -> -1662.4989 | H8: ='Cash Flow statement'!H32 -> -1737.3113 | I8: ='Cash Flow statement'!I32 -> -1815.4903
A9: Add: Changes in NWC | E9: =-('Working capital schedule'!E26-'Working capital schedule'!D26) -> -368.81591 | F9: =-('Working capital schedule'!F26-'Working capital schedule'!E26) -> -72.801716 | G9: =-('Working capital schedule'!G26-'Working capital schedule'!F26) -> -76.077793 | H9: =-('Working capital schedule'!H26-'Working capital schedule'!G26) -> -79.501294 | I9: =-('Working capital schedule'!I26-'Working capital schedule'!H26) -> -83.078852
A10: Unlevered Free Cash Flow (UFCF) | E10: =E7+E8+E9 -> 2948.5734 | F10: =F7+F8+F9 -> 3400.28 | G10: =G7+G8+G9 -> 3559.7025 | H10: =H7+H8+H9 -> 3726.299 | I10: =I7+I8+I9 -> 3900.3924
A12: Discount period | E12: 1 | F12: 2 | G12: 3 | H12: 4 | I12: 5
A13: Discount factor (1/(1 + r)^n) | E13: =1/((1+$F$52)^E12) -> 0.92268071 | F13: =1/((1+$F$52)^F12) -> 0.85133969 | G13: =1/((1+$F$52)^G12) -> 0.78551471 | H13: =1/((1+$F$52)^H12) -> 0.72477927 | I13: =1/((1+$F$52)^I12) -> 0.66873985
A14: Present value of UFCF | E14: =E10*E13 -> 2720.5918 | F14: =F10*F13 -> 2894.7933 | G14: =G10*G13 -> 2796.1987 | H14: =H10*H13 -> 2700.7443 | I14: =I10*I13 -> 2608.3478
A15: Terminal value
A17: Exit multiple method
A18: Exit EBITDA | E18: =I3+I6 -> 6569.6185
A19: EBITDA multiple | E19: =C28/I7 -> 11.72507 | F19: EV/EBITDA 2030
A20: Terminal value | E20: =E18*E19 -> 77029.236
A21: NPV of the terminal value | E21: =E20/((1+F52)^I12) -> 51512.52
A24: Perpetuity method | D24: TM(perpetuity method) = UFCF * (1+ g)/(r - g)
A25: Unlevered FCF (last period) | C25: =I10 -> 3900.3924
A26: Growth rate | C26: 0.025
A27: Discount rate | C27: =F52 -> 0.083798533
A28: Terminal value | C28: =C25*(1+C26)/(C27-C26) -> 67993.229
A29: NPV of the terminal value | C29: =C28/((1+C27)^I12) -> 45469.782
A31: Total value of firm | E31: Exit multiple | F31: Perpetuity
A32: NPV of the UFCF | E32: =SUM(E14:I14) -> 13720.676 | F32: 13720.676
A33: NPV of the TV | E33: =E21 -> 51512.52 | F33: =C29 -> 45469.782
A34: Total Enterprise value | E34: =SUM(E32:E33) -> 65233.196 | F34: =SUM(F32:F33) -> 59190.458
A35: Less: Net debt | E35: =F48-'Balance sheet'!D8 -> 10257 | F35: 10257
A36: Equity value | E36: =E34-E35 -> 54976.196 | F36: =F34-F35 -> 48933.458
A37: Shares outstanding | E37: =F50 -> 141.643 | F37: 141.643
A38: Price per share | E38: =E36/E37 -> 388.13211 | F38: =F36/F37 -> 345.47036
A41: Discount rate (Cost of capital)
A42: WACC = MV of equity / (MV of equity + MV of debt) * Ke + MV of debt / (MV of equity + MV of debt) * Kd (1-Tax rate)
A43: CAPM = Risk- free rate of return + (Beta * (Market risk premium))
A45: WACC Calculation | I45: Cost of equity (Using CAPM)
A46: Cost of equity | F46: =M52 -> 0.091352 | I46: Risk - free rate of return | M46: 0.0437
A47: Cost of debt | F47: ='Debt schedule'!E10 -> 0.043859649 | I47: Beta | M47: 1.14
A48: MV of debt | F48: ='Debt schedule'!E8 -> 14660 | I48: Market risk premium | M48: 0.0418
A49: Share price | F49: 557.47
A50: Shares outstanding | F50: ='Income statement'!E53 -> 141.643
A51: MV of equity | F51: =F49*F50 -> 78961.723
A52: WACC | F52: =((F51/(F51+F48))*F46)+((F48/(F51+F48))*F47*(1-0.017)) -> 0.083798533 | I52: Cost of equity | M52: =M46+(M47*M48) -> 0.091352

Sheet Comps
A2: Comparable Companies Analysis
C4: Market Data | I4: Financials | M4: Valuation
A5: Company | B5: Ticker | C5: Share Price | D5: Shares Outstanding | E5: Equity Value | F5: Net Debt | G5: Enterprise Value | I5: Revenue | J5: EBITDA | K5: Net Income | M5: EV/Revenue | N5: EV/EBITDA | O5: P/E
A7: Northrop Grumman | B7: NOC | C7: 547.23 | D7: 141.92 | E7: =C7*D7 -> 77662.882 | F7: 10759 | G7: =E7+F7 -> 88421.882 | I7: 41954 | J7: 6820 | K7: 4182 | M7: =$G7/I7 -> 2.1075912 | N7: =$G7/J7 -> 12.965085 | O7: =E7/K7 -> 18.570751
A8: Lockheed Martin | B8: LMT | C8: 560.99 | D8: 230.79 | E8: =C8*D8 -> 129470.88 | F8: =1168+20532-4121 -> 17579 | G8: =E8+F8 -> 147049.88 | I8: =75000 -> 75000 | J8: =8640+1560 -> 10200 | K8: 5017 | M8: =$G8/I8 -> 1.9606651 | N8: =$G8/J8 -> 14.416655 | O8: =E8/K8 -> 25.806435
A9: General Dynamics | B9: GD | C9: 379.07 | D9: 270.56 | E9: =C9*D9 -> 102561.18 | F9: =1006+7007-2333 -> 5680 | G9: =E9+F9 -> 108241.18 | I9: =52553 -> 52553 | J9: 7440 | K9: 4210 | M9: =$G9/I9 -> 2.0596575 | N9: =$G9/J9 -> 14.548546 | O9: =E9/K9 -> 24.361325
A10: Raytheon | B10: RTX | C10: 210.99 | D10: 1348 | E10: =C10*D10 -> 284414.52 | F10: =34215-7435 -> 26780 | G10: =E10+F10 -> 311194.52 | I10: 88603 | J10: =9302+4378 -> 13680 | K10: 6732 | M10: =$G10/I10 -> 3.5122346 | N10: =$G10/J10 -> 22.748137 | O10: =E10/K10 -> 42.248146
A12: High | M12: =MAX(M8:M10) -> 3.5122346 | N12: =MAX(N8:N10) -> 22.748137 | O12: =MAX(O8:O10) -> 42.248146
A13: 75th Percentile | M13: =QUARTILE(M8:M10,3) -> 2.785946 | N13: =QUARTILE(N8:N10,3) -> 18.648342 | O13: =QUARTILE(O8:O10,3) -> 34.02729
A14: Average | M14: =AVERAGE(M8:M10) -> 2.5108524 | N14: =AVERAGE(N8:N10) -> 17.237779 | O14: =AVERAGE(O8:O10) -> 30.805302
A15: Median | M15: =MEDIAN(M8:M10) -> 2.0596575 | N15: =MEDIAN(N8:N10) -> 14.548546 | O15: =MEDIAN(O8:O10) -> 25.806435
A16: 25th Percentile | M16: =QUARTILE(M8:M10,1) -> 2.0101613 | N16: =QUARTILE(N8:N10,1) -> 14.4826 | O16: =QUARTILE(O8:O10,1) -> 25.08388
A17: Low | M17: =MIN(M8:M10) -> 1.9606651 | N17: =MIN(N8:N10) -> 14.416655 | O17: =MIN(O8:O10) -> 24.361325
A19: Northrop Grumman Implied Valuation | M19: EV/Revenue | N19: EV/EBITDA | O19: P/E
A20: Implied Enterprise Value | M20: =M15*I7 -> 86410.87 | N20: =N15*J7 -> 99221.081 | O20: =O21+O22 -> 118681.51
A21: Net Debt | M21: =$F$7 -> 10759 | N21: =$F$7 -> 10759 | O21: =$F$7 -> 10759
A22: Implied Market Value | M22: =M20-M21 -> 75651.87 | N22: =N20-N21 -> 88462.081 | O22: =O15*K7 -> 107922.51
A23: Shares Outstanding | M23: =$D$7 -> 141.92 | N23: =$D$7 -> 141.92 | O23: =$D$7 -> 141.92
A24: Implied Value Per Share | M24: =M22/M23 -> 533.05996 | N24: =N22/N23 -> 623.32357 | O24: =O22/O23 -> 760.44609
